gurke/__init__.py
gurke/__main__.py
gurke/__version__.py
gurke/ast_builder.py
gurke/ast_node.py
gurke/count_symbols.py
gurke/dialect.py
gurke/errors.py
gurke/gherkin-languages.json
gurke/gherkin_line.py
gurke/location.py
gurke/parser.py
gurke/py.typed
gurke/token.py
gurke/token_formatter_builder.py
gurke/token_matcher.py
gurke/token_matcher_markdown.py
gurke/token_scanner.py
gurke/pickles/__init__.py
gurke/pickles/compiler.py
gurke/stream/__init__.py
gurke/stream/gherkin_events.py
gurke/stream/id_generator.py
gurke/stream/source_events.py
gurke-0.3.2.dist-info/METADATA
gurke-0.3.2.dist-info/WHEEL
gurke-0.3.2.dist-info/licenses/LICENSE.txt
gurke-0.3.2.dist-info/RECORD
